gradunwarp/__init__.py
gradunwarp/core/__init__.py
gradunwarp/core/coeffs.py
gradunwarp/core/globals.py
gradunwarp/core/gradient_unwarp.py
gradunwarp/core/unwarp_resample.py
gradunwarp/core/utils.py
gradunwarp/core/tests/__init__.py
gradunwarp/core/tests/test_gradient_unwarp.py
gradunwarp/core/tests/test_regression.py
gradunwarp/core/tests/data/gradunwarp_coeffs.grad
gradunwarp/core/tests/data/siemens_B_output.npz
gradunwarp-1.2.3.data/scripts/gradient_unwarp.py
gradunwarp-1.2.3.dist-info/METADATA
gradunwarp-1.2.3.dist-info/WHEEL
gradunwarp-1.2.3.dist-info/top_level.txt
gradunwarp-1.2.3.dist-info/RECORD
