Metadata-Version: 2.1
Name: gradunwarp
Version: 1.2.3
Summary: HCP version of Gradient Unwarping Package for Python/Numpy
Author: Human Connectome Project
Classifier: Development Status :: 6 - Mature
Classifier: License :: OSI Approved :: MIT License
Classifier: Programming Language :: Python :: 2.7
Classifier: Programming Language :: Python :: 3.6
Classifier: Programming Language :: Python :: 3.7
Classifier: Programming Language :: Python :: 3.8
Classifier: Programming Language :: Python :: 3.9
Classifier: Programming Language :: Python :: 3.10
Classifier: Programming Language :: Python :: 3.11
Classifier: Programming Language :: Python :: 3.12
Classifier: Operating System :: OS Independent
Classifier: Topic :: Scientific/Engineering :: Image Processing
Classifier: Topic :: Scientific/Engineering :: Medical Science Apps.
Requires-Dist: nibabel>=3.2.1; python_version >= "3.0"
Requires-Dist: nibabel>=2.0; python_version < "3.0"
Requires-Dist: numpy
Requires-Dist: scipy
